vsa_explainer/__init__.py
vsa_explainer/explainer.py
vsa_explainer-0.2.0.dist-info/.ipynb_checkpoints/top_level-checkpoint.txt
vsa_explainer-0.2.0.dist-info/METADATA
vsa_explainer-0.2.0.dist-info/WHEEL
vsa_explainer-0.2.0.dist-info/entry_points.txt
vsa_explainer-0.2.0.dist-info/top_level.txt
vsa_explainer-0.2.0.dist-info/RECORD
