Metadata-Version: 2.4
Name: vsa_explainer
Version: 0.2.0
Summary: Visualize and explain RDKit VSA descriptor contributions
Home-page: https://github.com/srijitseal/vsa_explainer
Author: Srijit Seal
Author-email: seal@understanding.bio
License: MIT
Classifier: Programming Language :: Python :: 3
Classifier: License :: OSI Approved :: MIT License
Requires-Python: >=3.8
Requires-Dist: numpy>=1.18
Requires-Dist: matplotlib>=3.0
Requires-Dist: rdkit
Requires-Dist: ipython
Provides-Extra: dev
Requires-Dist: pytest; extra == "dev"
Dynamic: author
Dynamic: author-email
Dynamic: classifier
Dynamic: description
Dynamic: description-content-type
Dynamic: home-page
Dynamic: license
Dynamic: provides-extra
Dynamic: requires-dist
Dynamic: requires-python
Dynamic: summary
